vqrcoinrpc/__init__.py
vqrcoinrpc/__version__.py
vqrcoinrpc/_exceptions.py
vqrcoinrpc/_types.py
vqrcoinrpc/bitcoin_rpc.py
vqrcoinrpc-0.6.4.dist-info/LICENSE
vqrcoinrpc-0.6.4.dist-info/METADATA
vqrcoinrpc-0.6.4.dist-info/WHEEL
vqrcoinrpc-0.6.4.dist-info/top_level.txt
vqrcoinrpc-0.6.4.dist-info/RECORD
