Metadata-Version: 2.1
Name: vqrcoinrpc
Version: 0.6.4
Summary: Lightweight VQR JSON-RPC Python asynchronous client
Home-page: https://github.com/surugh/vqr-python-async-rpc
Author: Libor Martinek, Peerchemist, Surugh
Author-email: surugh@gmail.com
License: MIT
Keywords: vqr async json-rpc
Classifier: Development Status :: 4 - Beta
Classifier: Intended Audience :: Developers
Classifier: Programming Language :: Python
Classifier: Programming Language :: Python :: 3.7
Classifier: Programming Language :: Python :: 3.8
Classifier: Programming Language :: Python :: 3.9
Classifier: Programming Language :: Python :: 3.10
Classifier: Programming Language :: Python :: 3.11
Classifier: Programming Language :: Python :: 3 :: Only
Classifier: Topic :: Software Development :: Libraries :: Python Modules
Requires-Python: >=3.7
License-File: LICENSE
Requires-Dist: orjson >=3
Requires-Dist: httpx <1
Requires-Dist: typing-extensions >=3.7.4.3
Requires-Dist: bitcoinrpc ~=0.6.1
Requires-Dist: setuptools ==69.0.3
